ssh_manager/__init__.py
ssh_manager/parser.py
ssh_manager/viewer.py
sshmgm-1.0.3.dist-info/LICENSE
sshmgm-1.0.3.dist-info/METADATA
sshmgm-1.0.3.dist-info/WHEEL
sshmgm-1.0.3.dist-info/entry_points.txt
sshmgm-1.0.3.dist-info/top_level.txt
sshmgm-1.0.3.dist-info/RECORD
