Metadata-Version: 2.1
Name: sshmgm
Version: 1.0.3
Summary: A tool for parsing and displaying SSH connection history
Home-page: https://github.com/htayanloo/SSH-Manager
Author: Hadi Tayanloo
Author-email: htayanloo@example.com
Classifier: Programming Language :: Python :: 3
Classifier: License :: OSI Approved :: MIT License
Classifier: Operating System :: OS Independent
Requires-Python: >=3.6
License-File: LICENSE
Requires-Dist: rich
